glue_medical/__init__.py
glue_medical/dicom_factory.py
glue_medical/dicom_importer.py
glue_medical/tests/__init__.py
glue_medical/tests/test_dicom_factory.py
glue_medical/tests/data/CT_small.dcm
glue_medical/tests/data/LICENSE
glue_medical/tests/data/__init__.py
glue_medical/tests/data/dicom_directory/15970
glue_medical/tests/data/dicom_directory/4950
glue_medical/tests/data/dicom_directory/4981
glue_medical/tests/data/dicom_directory/5011
glue_medical/tests/data/dicom_directory/6273
glue_medical/tests/data/dicom_directory/6605
glue_medical/tests/data/dicom_directory/6935
glue_medical/tests/data/dicom_heterogeneous_directory/file1.dcm
glue_medical/tests/data/dicom_heterogeneous_directory/file2.dcm
glue_medical-0.2.dist-info/LICENSE
glue_medical-0.2.dist-info/METADATA
glue_medical-0.2.dist-info/WHEEL
glue_medical-0.2.dist-info/entry_points.txt
glue_medical-0.2.dist-info/top_level.txt
glue_medical-0.2.dist-info/zip-safe
glue_medical-0.2.dist-info/RECORD
