Metadata-Version: 2.1
Name: glue-medical
Version: 0.2
Summary: Plugin for glue to support medical data
Home-page: https://github.com/glue-viz/glue-medical
License: UNKNOWN
Platform: UNKNOWN
Requires-Dist: numpy
Requires-Dist: glue-core (>=0.12)
Requires-Dist: pydicom
Provides-Extra: test
Requires-Dist: pytest ; extra == 'test'
Requires-Dist: pytest-cov ; extra == 'test'
Requires-Dist: pytest-faulthandler ; extra == 'test'
